moonspark/__init__.py
moonspark/logging.py
moonspark/polars.py
moonspark/types.py
moonspark-0.1.0.dist-info/METADATA
moonspark-0.1.0.dist-info/WHEEL
moonspark-0.1.0.dist-info/RECORD
